dev_pipeline_git-0.4.4.dist-info/DESCRIPTION.rst
dev_pipeline_git-0.4.4.dist-info/METADATA
dev_pipeline_git-0.4.4.dist-info/RECORD
dev_pipeline_git-0.4.4.dist-info/WHEEL
dev_pipeline_git-0.4.4.dist-info/entry_points.txt
dev_pipeline_git-0.4.4.dist-info/metadata.json
dev_pipeline_git-0.4.4.dist-info/top_level.txt
devpipeline_git/__init__.py
devpipeline_git/git.py
