Metadata-Version: 2.0
Name: dev-pipeline-git
Version: 0.4.4
Summary: git plugin for dev-pipeline
Home-page: https://github.com/dev-pipeline/dev-pipeline-git
Author: Stephen Newell
License: BSD-2
Platform: UNKNOWN
Classifier: Development Status :: 2 - Pre-Alpha
Classifier: Environment :: Plugins
Classifier: Intended Audience :: Developers
Classifier: License :: OSI Approved :: BSD License
Classifier: Topic :: Software Development
Classifier: Topic :: Software Development :: Version Control :: Git
Classifier: Topic :: Utilities
Requires-Dist: dev-pipeline-core (>=0.4.0)
Requires-Dist: dev-pipeline-scm (>=0.4.0)
